pyshopify/__init__.py
pyshopify/api.py
pyshopify/cli.py
pyshopify/configure.py
pyshopify/csv_out.py
pyshopify/db_model.py
pyshopify/return_parse.py
pyshopify/runner.py
pyshopify/sql.py
pyshopify/vars.py
pyshopify-0.9.11.dist-info/LICENSE
pyshopify-0.9.11.dist-info/METADATA
pyshopify-0.9.11.dist-info/WHEEL
pyshopify-0.9.11.dist-info/entry_points.txt
pyshopify-0.9.11.dist-info/top_level.txt
pyshopify-0.9.11.dist-info/RECORD
