Metadata-Version: 2.1
Name: pyshopify
Version: 0.9.11
Summary: Shopify Orders & Customers API library with containerized         MS SQL database
Home-page: https://github.com/pyshopify
Author: Joseph Trabulsy
Author-email: webdjoe@gmail.com
Project-URL: Bug Tracker, https://github.com/pyshopify/issues
Keywords: shopify,sql server,mssql,python,docker,python3,pyodbc
Classifier: Programming Language :: Python :: 3.9
Classifier: License :: OSI Approved :: MIT License
Classifier: Operating System :: OS Independent
Requires-Python: >=3.9
License-File: LICENSE
Requires-Dist: click (>=8.0.1)
Requires-Dist: numpy (>=1.20.3)
Requires-Dist: pandas (>=1.2.4)
Requires-Dist: python-dateutil
Requires-Dist: requests (>=2.20)
Requires-Dist: tzdata
Requires-Dist: sqlalchemy (>=1.4.1)
